{
  "url": "https://mosdac.gov.in/internal/uops",
  "depth": 6,
  "page_type": "internal",
  "title": "Log in to MOSDAC Single Sign ON",
  "extracted_content": null,
  "links": {
    "internal": [
      {
        "href": "https://mosdac.gov.in",
        "text": "Home (मुख पृष्ठ)",
        "title": "",
        "base_domain": "mosdac.gov.in"
      },
      {
        "href": "https://mosdac.gov.in/auth/realms/Mosdac/protocol/openid-connect/auth?response_type=code&scope=openid%20email&client_id=mosdac&state=umvByUjXX57UzKLENCPFjXQeq1s&redirect_uri=https%3A%2F%2Fmosdac.gov.in%2Fuops%2Fredirect_uri&nonce=9tFJrANr0Cu7OTlP-_rkl5aUZL4rQX94A4jzD2YazoE/",
        "text": "English",
        "title": "",
        "base_domain": "mosdac.gov.in"
      },
      {
        "href": "https://mosdac.gov.in/auth/realms/Mosdac/login-actions/authenticate?client_id=mosdac&tab_id=PP9EjbmG5j4&execution=9df053f1-55e1-4d2c-b1ae-a86b988114ed&kc_locale=hi",
        "text": "Hindi",
        "title": "",
        "base_domain": "mosdac.gov.in"
      },
      {
        "href": "https://mosdac.gov.in/auth/realms/Mosdac/login-actions/authenticate?client_id=mosdac&tab_id=PP9EjbmG5j4&execution=9df053f1-55e1-4d2c-b1ae-a86b988114ed&kc_locale=en",
        "text": "English",
        "title": "",
        "base_domain": "mosdac.gov.in"
      },
      {
        "href": "https://mosdac.gov.in/auth/realms/Mosdac/login-actions/reset-credentials?client_id=mosdac&tab_id=PP9EjbmG5j4",
        "text": "Forgot Password?",
        "title": "",
        "base_domain": "mosdac.gov.in"
      }
    ],
    "external": []
  },
  "media": {
    "images": [],
    "videos": [],
    "audios": []
  },
  "metadata": {
    "title": "Log in to MOSDAC Single Sign ON",
    "description": null,
    "keywords": null,
    "author": null
  },
  "crawl_timestamp": "2025-06-26 13:27:22"
}